openplugin/__init__.py
openplugin/__main__.py
openplugin/actions/action_group_execution_pipeline.py
openplugin/actions/action_group_input.py
openplugin/api/__init__.py
openplugin/api/action_group_execution_pipeline.py
openplugin/api/application.py
openplugin/api/auth.py
openplugin/api/function_providers.py
openplugin/api/helpers.py
openplugin/api/http_error.py
openplugin/api/info.py
openplugin/api/operation_execution.py
openplugin/api/operation_signature_builder.py
openplugin/api/plugin_execution_pipeline.py
openplugin/api/plugin_selector.py
openplugin/api/processors.py
openplugin/core/__init__.py
openplugin/core/config.py
openplugin/core/execution/implementations/operation_execution_with_imprompt.py
openplugin/core/execution/operation_execution.py
openplugin/core/flow_path.py
openplugin/core/function_providers.py
openplugin/core/functions.py
openplugin/core/helper.py
openplugin/core/messages.py
openplugin/core/operations/implementations/operation_signature_builder_custom.py
openplugin/core/operations/implementations/operation_signature_builder_with_imprompt.py
openplugin/core/operations/implementations/operation_signature_builder_with_langchain.py
openplugin/core/operations/implementations/operation_signature_builder_with_openai.py
openplugin/core/operations/operation_signature_builder.py
openplugin/core/plugin.py
openplugin/core/plugin_detected.py
openplugin/core/plugin_execution_pipeline.py
openplugin/core/plugin_runner.py
openplugin/core/port.py
openplugin/core/selectors/implementations/plugin_selector_with_imprompt.py
openplugin/core/selectors/implementations/plugin_selector_with_langchain.py
openplugin/core/selectors/implementations/plugin_selector_with_openai.py
openplugin/core/selectors/plugin_selector.py
openplugin/main.py
openplugin/processors/__init__.py
openplugin/processors/audio_to_text/audio_to_text.py
openplugin/processors/audio_to_text/audio_to_text_factory.py
openplugin/processors/audio_to_text/implementations/audio_to_text_with_whisper.py
openplugin-0.1.8.dist-info/LICENSE
openplugin-0.1.8.dist-info/METADATA
openplugin-0.1.8.dist-info/WHEEL
openplugin-0.1.8.dist-info/entry_points.txt
openplugin-0.1.8.dist-info/RECORD
